shibumi/__init__.py
shibumi/diagram_writer.py
shibumi/play_shibumi.py
shibumi/shibumi.py
shibumi/shibumi_display.py
shibumi/shibumi_display_ui.py
shibumi/shibumi_game_state.py
shibumi/shibumi_images_rc.py
shibumi/shibumi_rules_rc.py
shibumi/margo/__init__.py
shibumi/margo/display.py
shibumi/margo/state.py
shibumi/sandbox/__init__.py
shibumi/sandbox/display.py
shibumi/sandbox/game.py
shibumi/spaiji/__init__.py
shibumi/spaiji/display.py
shibumi/spaiji/game.py
shibumi/spargo/__init__.py
shibumi/spargo/display.py
shibumi/spargo/game.py
shibumi/sparks/__init__.py
shibumi/sparks/display.py
shibumi/sparks/state.py
shibumi/spire/__init__.py
shibumi/spire/display.py
shibumi/spire/state.py
shibumi/spline/__init__.py
shibumi/spline/display.py
shibumi/spline/game.py
shibumi/sploof/__init__.py
shibumi/sploof/display.py
shibumi/sploof/state.py
shibumi/spook/__init__.py
shibumi/spook/display.py
shibumi/spook/state.py
shibumi/utils/__init__.py
shibumi/utils/headcount.py
tests/__init__.py
tests/conftest.py
shibumi-0.5.0.dist-info/LICENSE
shibumi-0.5.0.dist-info/METADATA
shibumi-0.5.0.dist-info/WHEEL
shibumi-0.5.0.dist-info/entry_points.txt
shibumi-0.5.0.dist-info/top_level.txt
shibumi-0.5.0.dist-info/RECORD
