Metadata-Version: 2.1
Name: shibumi
Version: 0.5.0
Summary: Simple board games hiding complexity
Home-page: https://donkirkby.github.io/shibumi-games/
Author: Don Kirkby
Project-URL: Bug Reports, https://github.com/donkirkby/shibumi-games/issues
Project-URL: Source, https://github.com/donkirkby/shibumi-games
Keywords: boardgames alphazero machine learning mcts shibumi
Classifier: Development Status :: 3 - Alpha
Classifier: Intended Audience :: Developers
Classifier: Topic :: Games/Entertainment :: Board Games
Classifier: License :: OSI Approved :: MIT License
Classifier: Programming Language :: Python :: 3.8
License-File: LICENSE
Requires-Dist: zero-play
Requires-Dist: numpy
Provides-Extra: ml
Requires-Dist: zero-play[ml] ; extra == 'ml'
Provides-Extra: ml-gpu
Requires-Dist: zero-play[ml-gpu] ; extra == 'ml-gpu'
